Workbook

Sheet Carteira
A1: Carteira de Investimentos
A2: Preencha as células em amarelo (Ticker, Tipo, Quantidade, Preço Médio, Preço Atual). As demais colunas são calculadas automaticamente.
A4: Ticker | B4: Tipo de Ativo | C4: Quantidade | D4: Preço Médio (R$) | E4: Preço Atual (R$) | F4: Valor Investido (R$) | G4: Valor Atual (R$) | H4: Rentabilidade (R$) | I4: Rentabilidade (%) | J4: Proventos Recebidos (R$)
A5: PETR4 | B5: Ação | C5: 100 | D5: 28.5 | E5: 35.2 | F5: =C5*D5 -> 2850 | G5: =C5*E5 -> 3520 | H5: =G5-F5 -> 670 | I5: =IF(F5=0,0,H5/F5) -> 0.23508772 | J5: =SUMIF(Proventos!$B:$B,A5,Proventos!$D:$D) -> 77
A6: VALE3 | B6: Ação | C6: 50 | D6: 62 | E6: 58.4 | F6: =C6*D6 -> 3100 | G6: =C6*E6 -> 2920 | H6: =G6-F6 -> -180 | I6: =IF(F6=0,0,H6/F6) -> -0.058064516 | J6: =SUMIF(Proventos!$B:$B,A6,Proventos!$D:$D) -> 0
A7: ITUB4 | B7: Ação | C7: 80 | D7: 27.8 | E7: 32.1 | F7: =C7*D7 -> 2224 | G7: =C7*E7 -> 2568 | H7: =G7-F7 -> 344 | I7: =IF(F7=0,0,H7/F7) -> 0.15467626 | J7: =SUMIF(Proventos!$B:$B,A7,Proventos!$D:$D) -> 22.5
A8: HGLG11 | B8: FII | C8: 40 | D8: 165 | E8: 172.5 | F8: =C8*D8 -> 6600 | G8: =C8*E8 -> 6900 | H8: =G8-F8 -> 300 | I8: =IF(F8=0,0,H8/F8) -> 0.045454545 | J8: =SUMIF(Proventos!$B:$B,A8,Proventos!$D:$D) -> 117.5
A9: MXRF11 | B9: FII | C9: 200 | D9: 10.2 | E9: 9.85 | F9: =C9*D9 -> 2040 | G9: =C9*E9 -> 1970 | H9: =G9-F9 -> -70 | I9: =IF(F9=0,0,H9/F9) -> -0.034313725 | J9: =SUMIF(Proventos!$B:$B,A9,Proventos!$D:$D) -> 73.3
A10: IVVB11 | B10: ETF | C10: 30 | D10: 270 | E10: 305 | F10: =C10*D10 -> 8100 | G10: =C10*E10 -> 9150 | H10: =G10-F10 -> 1050 | I10: =IF(F10=0,0,H10/F10) -> 0.12962963 | J10: =SUMIF(Proventos!$B:$B,A10,Proventos!$D:$D) -> 0
A11: Tesouro Selic 2029 | B11: Renda Fixa | C11: 1 | D11: 12500 | E11: 13100 | F11: =C11*D11 -> 12500 | G11: =C11*E11 -> 13100 | H11: =G11-F11 -> 600 | I11: =IF(F11=0,0,H11/F11) -> 0.048 | J11: =SUMIF(Proventos!$B:$B,A11,Proventos!$D:$D) -> 0
A12: BTC | B12: Cripto | C12: 0.05 | D12: 250000 | E12: 310000 | F12: =C12*D12 -> 12500 | G12: =C12*E12 -> 15500 | H12: =G12-F12 -> 3000 | I12: =IF(F12=0,0,H12/F12) -> 0.24 | J12: =SUMIF(Proventos!$B:$B,A12,Proventos!$D:$D) -> 0
A13: TOTAL | F13: =SUM(F5:F12) -> 49914 | G13: =SUM(G5:G12) -> 55628 | H13: =G13-F13 -> 5714 | I13: =IF(F13=0,0,H13/F13) -> 0.1144769 | J13: =SUM(J5:J12) -> 290.3

Sheet Movimentações
A1: Movimentações (Compras e Vendas)
A2: Registre aqui cada compra ou venda. O Total é calculado somando taxas na compra e descontando taxas na venda.
A4: Data | B4: Ativo | C4: Tipo | D4: Quantidade | E4: Preço (R$) | F4: Taxas (R$) | G4: Total (R$)
A5: 45672 | B5: PETR4 | C5: Compra | D5: 60 | E5: 28.1 | F5: 4.9 | G5: =IF(C5="Compra",D5*E5+F5,D5*E5-F5) -> 1690.9
A6: 45726 | B6: PETR4 | C6: Compra | D6: 40 | E6: 29 | F6: 4.9 | G6: =IF(C6="Compra",D6*E6+F6,D6*E6-F6) -> 1164.9
A7: 45693 | B7: VALE3 | C7: Compra | D7: 50 | E7: 62 | F7: 5.2 | G7: =IF(C7="Compra",D7*E7+F7,D7*E7-F7) -> 3105.2
A8: 45677 | B8: ITUB4 | C8: Compra | D8: 80 | E8: 27.8 | F8: 6.1 | G8: =IF(C8="Compra",D8*E8+F8,D8*E8-F8) -> 2230.1
A9: 45759 | B9: HGLG11 | C9: Compra | D9: 40 | E9: 165 | F9: 3.8 | G9: =IF(C9="Compra",D9*E9+F9,D9*E9-F9) -> 6603.8
A10: 45795 | B10: MXRF11 | C10: Compra | D10: 200 | E10: 10.2 | F10: 2.5 | G10: =IF(C10="Compra",D10*E10+F10,D10*E10-F10) -> 2042.5
A11: 45713 | B11: IVVB11 | C11: Compra | D11: 30 | E11: 270 | F11: 7 | G11: =IF(C11="Compra",D11*E11+F11,D11*E11-F11) -> 8107
A12: 45809 | B12: Tesouro Selic 2029 | C12: Compra | D12: 1 | E12: 12500 | F12: 0 | G12: =IF(C12="Compra",D12*E12+F12,D12*E12-F12) -> 12500
A13: 45846 | B13: BTC | C13: Compra | D13: 0.05 | E13: 250000 | F13: 15 | G13: =IF(C13="Compra",D13*E13+F13,D13*E13-F13) -> 12515
A14: 46032 | B14: MXRF11 | C14: Venda | D14: 20 | E14: 9.9 | F14: 1.5 | G14: =IF(C14="Compra",D14*E14+F14,D14*E14-F14) -> 196.5

Sheet Proventos
A1: Proventos Recebidos (Dividendos, JCP, Rendimentos)
A2: Registre aqui cada provento recebido. A coluna Mês/Ano é usada no resumo do Dashboard.
A4: Data | B4: Ativo | C4: Tipo | D4: Valor (R$) | E4: Mês/Ano
A5: 45975 | B5: PETR4 | C5: Dividendo | D5: 45 | E5: =TEXT(A5,"MM/YYYY") -> 11/2025
A6: 46001 | B6: HGLG11 | C6: Rendimento | D6: 38.4 | E6: =TEXT(A6,"MM/YYYY") -> 12/2025
A7: 46001 | B7: MXRF11 | C7: Rendimento | D7: 20 | E7: =TEXT(A7,"MM/YYYY") -> 12/2025
A8: 46036 | B8: PETR4 | C8: JCP | D8: 32 | E8: =TEXT(A8,"MM/YYYY") -> 01/2026
A9: 46032 | B9: HGLG11 | C9: Rendimento | D9: 39.1 | E9: =TEXT(A9,"MM/YYYY") -> 01/2026
A10: 46032 | B10: MXRF11 | C10: Rendimento | D10: 18.6 | E10: =TEXT(A10,"MM/YYYY") -> 01/2026
A11: 46058 | B11: ITUB4 | C11: JCP | D11: 22.5 | E11: =TEXT(A11,"MM/YYYY") -> 02/2026
A12: 46063 | B12: HGLG11 | C12: Rendimento | D12: 40 | E12: =TEXT(A12,"MM/YYYY") -> 02/2026
A13: 46063 | B13: MXRF11 | C13: Rendimento | D13: 17.9 | E13: =TEXT(A13,"MM/YYYY") -> 02/2026
A14: 46091 | B14: MXRF11 | C14: Rendimento | D14: 16.8 | E14: =TEXT(A14,"MM/YYYY") -> 03/2026

Sheet Dashboard
A1: Dashboard - Resumo da Carteira
A3: Resumo Geral
A4: Total Investido | B4: =Carteira!F13 -> 49914
A5: Valor Atual da Carteira | B5: =Carteira!G13 -> 55628
A6: Rentabilidade (R$) | B6: =Carteira!H13 -> 5714
A7: Rentabilidade (%) | B7: =Carteira!I13 -> 0.1144769
A8: Total de Proventos Recebidos | B8: =Carteira!J13 -> 290.3
A9: Quantidade de Ativos | B9: =COUNTA(Carteira!A5:A12) -> 8
A11: Alocação por Tipo de Ativo
A12: Tipo de Ativo | B12: Valor Atual (R$) | C12: % da Carteira
A13: Ação | B13: =SUMIF(Carteira!$B$5:$B$12,A13,Carteira!$G$5:$G$12) -> 9008 | C13: =IF($B$5=0,0,B13/$B$5) -> 0.16193284
A14: FII | B14: =SUMIF(Carteira!$B$5:$B$12,A14,Carteira!$G$5:$G$12) -> 8870 | C14: =IF($B$5=0,0,B14/$B$5) -> 0.15945207
A15: ETF | B15: =SUMIF(Carteira!$B$5:$B$12,A15,Carteira!$G$5:$G$12) -> 9150 | C15: =IF($B$5=0,0,B15/$B$5) -> 0.16448551
A16: Renda Fixa | B16: =SUMIF(Carteira!$B$5:$B$12,A16,Carteira!$G$5:$G$12) -> 13100 | C16: =IF($B$5=0,0,B16/$B$5) -> 0.23549292
A17: Cripto | B17: =SUMIF(Carteira!$B$5:$B$12,A17,Carteira!$G$5:$G$12) -> 15500 | C17: =IF($B$5=0,0,B17/$B$5) -> 0.27863666
A18: Outro | B18: =SUMIF(Carteira!$B$5:$B$12,A18,Carteira!$G$5:$G$12) -> 0 | C18: =IF($B$5=0,0,B18/$B$5) -> 0
A20: Proventos Recebidos por Mês
A21: Mês/Ano | B21: Total Recebido (R$)
A22: 01/2026 | B22: =SUMIF(Proventos!$E$5:$E$14,A22,Proventos!$D$5:$D$14) -> 89.7
A23: 02/2026 | B23: =SUMIF(Proventos!$E$5:$E$14,A23,Proventos!$D$5:$D$14) -> 80.4
A24: 03/2026 | B24: =SUMIF(Proventos!$E$5:$E$14,A24,Proventos!$D$5:$D$14) -> 16.8
A25: 11/2025 | B25: =SUMIF(Proventos!$E$5:$E$14,A25,Proventos!$D$5:$D$14) -> 45
A26: 12/2025 | B26: =SUMIF(Proventos!$E$5:$E$14,A26,Proventos!$D$5:$D$14) -> 58.4
A28: Observação: os valores desta planilha são exemplos ilustrativos. Substitua pelos seus dados reais nas abas Carteira, Movimentações e Proventos.
